echopop/__init__.py
echopop/_testing.py
echopop/_version.py
echopop/utils.py
echopop/core/__init__.py
echopop/core/echoview.py
echopop/core/validators.py
echopop/geostatistics/__init__.py
echopop/geostatistics/cropping.py
echopop/geostatistics/kriging.py
echopop/geostatistics/projection.py
echopop/geostatistics/variogram.py
echopop/geostatistics/variogram_models.py
echopop/graphics/__init__.py
echopop/graphics/age_length_heatmap.py
echopop/graphics/diagnostics.py
echopop/graphics/kriged_mesh.py
echopop/graphics/transect_map.py
echopop/graphics/utils.py
echopop/graphics/variogram_gui.py
echopop/ingest/__init__.py
echopop/ingest/biological.py
echopop/ingest/mesh.py
echopop/ingest/nasc.py
echopop/ingest/params.py
echopop/ingest/strata.py
echopop/ingest/sv.py
echopop/inversion/__init__.py
echopop/inversion/inversion_base.py
echopop/inversion/inversion_length_TS.py
echopop/inversion/inversion_matrix.py
echopop/inversion/pcdwba.py
echopop/inversion/post_inversion.py
echopop/inversion/utils.py
echopop/survey/__init__.py
echopop/survey/biology.py
echopop/survey/proportions.py
echopop/survey/statistics.py
echopop/survey/stratified.py
echopop/survey/transect.py
echopop/tests/__init__.py
echopop/tests/conftest.py
echopop/tests/fixtures/__init__.py
echopop/tests/fixtures/fixtures_basic_plotting.py
echopop/tests/fixtures/fixtures_binning.py
echopop/tests/fixtures/fixtures_biodata_loader.py
echopop/tests/fixtures/fixtures_biology.py
echopop/tests/fixtures/fixtures_cropping.py
echopop/tests/fixtures/fixtures_data_loader.py
echopop/tests/fixtures/fixtures_echoview_ingestion.py
echopop/tests/fixtures/fixtures_geostatistics_loader.py
echopop/tests/fixtures/fixtures_geostats_class.py
echopop/tests/fixtures/fixtures_inversion.py
echopop/tests/fixtures/fixtures_kriging.py
echopop/tests/fixtures/fixtures_partition_transect.py
echopop/tests/fixtures/fixtures_proportions.py
echopop/tests/fixtures/fixtures_spatial.py
echopop/tests/fixtures/fixtures_statistics.py
echopop-0.5.0.dist-info/licenses/LICENSE
echopop-0.5.0.dist-info/METADATA
echopop-0.5.0.dist-info/WHEEL
echopop-0.5.0.dist-info/top_level.txt
echopop-0.5.0.dist-info/RECORD
