Metadata-Version: 2.4
Name: echopop
Version: 0.5.0
Summary: A tool to generate biological estimates from acoustic data collected from echosounders
Author-email: Brandyn Lucca <brandyn.lucca@gmail.com>
Maintainer-email: Wu-Jung Lee <leewujung@gmail.com>
License: Apache License, Version 2.0
Project-URL: Homepage, https://github.com/OSOceanAcoustics/echopop
Classifier: Development Status :: 4 - Beta
Classifier: Environment :: Console
Classifier: Intended Audience :: Science/Research
Classifier: License :: OSI Approved :: Apache Software License
Classifier: Operating System :: OS Independent
Classifier: Programming Language :: Python :: 3.9
Classifier: Topic :: Scientific/Engineering
Requires-Python: >=3.9
License-File: LICENSE
Requires-Dist: awkward
Requires-Dist: lmfit
Requires-Dist: numpy
Requires-Dist: openpyxl
Requires-Dist: pandas
Requires-Dist: scipy
Requires-Dist: numba
Requires-Dist: cartopy
Requires-Dist: geopandas
Requires-Dist: geopy
Requires-Dist: pyproj
Requires-Dist: shapely
Requires-Dist: verde
Requires-Dist: pandera>=0.25
Requires-Dist: pydantic>=2.0.0
Requires-Dist: traitlets
Requires-Dist: ipympl
Requires-Dist: jupyter_bokeh>=3.0.5
Requires-Dist: matplotlib
Requires-Dist: bokeh
Requires-Dist: geoviews
Requires-Dist: holoviews
Requires-Dist: ipywidgets
Dynamic: license-file
